Metadata-Version: 2.1
Name: huskoll
Version: 0.1.2
Summary: Python Wrapper around the Huskoll API.
Home-page: https://github.com/sotpotatis/Huskoll-Python
Author: sotpotatis
License: MIT
Keywords: api,huskoll
Platform: UNKNOWN
Classifier: Development Status :: 4 - Beta
Classifier: Intended Audience :: Developers
Classifier: License :: OSI Approved :: MIT License
Classifier: Programming Language :: Python :: 3
Classifier: Programming Language :: Python :: 3.4
Classifier: Programming Language :: Python :: 3.5
Classifier: Programming Language :: Python :: 3.6
Classifier: Programming Language :: Python :: 3.7
